orcestradownloader/__init__.py
orcestradownloader/cache.py
orcestradownloader/dataset_config.py
orcestradownloader/logging_config.py
orcestradownloader/managers.py
orcestradownloader/cli/__init__.py
orcestradownloader/cli/cli.py
orcestradownloader/models/__init__.py
orcestradownloader/models/base.py
orcestradownloader/models/clinical_icb.py
orcestradownloader/models/clinicalgenomics.py
orcestradownloader/models/common.py
orcestradownloader/models/pset.py
orcestradownloader/models/radiomicset.py
orcestradownloader/models/radioset.py
orcestradownloader/models/toxicoset.py
orcestradownloader/models/xevaset.py
orcestra_downloader-0.15.0.dist-info/METADATA
orcestra_downloader-0.15.0.dist-info/WHEEL
orcestra_downloader-0.15.0.dist-info/entry_points.txt
orcestra_downloader-0.15.0.dist-info/licenses/LICENSE
orcestra_downloader-0.15.0.dist-info/RECORD
