Metadata-Version: 2.4
Name: orcestra-downloader
Version: 0.15.0
Summary: Simplified access to download data from orcestra.ca
Project-URL: homepage, https://github.com/bhklab/orcestra-downloader
Project-URL: repository, https://github.com/bhklab/orcestra-downloader
Project-URL: documentation, https://bhklab.github.io/orcestra-downloader/
Project-URL: changelog, https://github.com/bhklab/orcestra-downloader/blob/main/docs/CHANGELOG.md
Project-URL: issues, https://github.com/bhklab/orcestra-downloader/issues
Author-email: Jermiah Joseph <jermiahjoseph98@gmail.com>
Maintainer-email: Jermiah Joseph <jermiahjoseph98@gmail.com>
License-Expression: MIT
License-File: LICENSE
Keywords: orcestra-downloader,pixi,python
Classifier: Development Status :: 1 - Planning
Classifier: License :: OSI Approved :: MIT License
Classifier: Operating System :: OS Independent
Classifier: Programming Language :: Python :: 3
Classifier: Programming Language :: Python :: 3.10
Classifier: Programming Language :: Python :: 3.11
Classifier: Programming Language :: Python :: 3.12
Classifier: Programming Language :: Python :: 3.13
Requires-Python: >=3.10
Requires-Dist: aiohttp>=3.11.4
Requires-Dist: click>=8.1.7
Requires-Dist: rich
